demcompare/__init__.py
demcompare/dataset_tools.py
demcompare/dem_tools.py
demcompare/demcompare.py
demcompare/demcompare_tiles.py
demcompare/helpers_init.py
demcompare/img_tools.py
demcompare/internal_typing.py
demcompare/log_conf.py
demcompare/logging.json
demcompare/report.py
demcompare/sphinx_project_generator.py
demcompare/stats_dataset.py
demcompare/stats_processing.py
demcompare/transformation.py
demcompare/classification_layer/__init__.py
demcompare/classification_layer/classification_layer.py
demcompare/classification_layer/classification_layer_template.py
demcompare/classification_layer/fusion_classification.py
demcompare/classification_layer/global_classification.py
demcompare/classification_layer/segmentation_classification.py
demcompare/classification_layer/slope_classification.py
demcompare/coregistration/__init__.py
demcompare/coregistration/coregistration.py
demcompare/coregistration/coregistration_template.py
demcompare/coregistration/nuth_kaab_internal.py
demcompare/dem_processing/__init__.py
demcompare/dem_processing/dem_processing.py
demcompare/dem_processing/dem_processing_methods.py
demcompare/dem_processing/dem_processing_template.py
demcompare/geoid/egm96_15.gtx
demcompare/metric/__init__.py
demcompare/metric/matrix_2d_metrics.py
demcompare/metric/metric.py
demcompare/metric/metric_template.py
demcompare/metric/scalar_metrics.py
demcompare/metric/vector_metrics.py
report/__init__.py
report/app.py
report/assets/__init__.py
report/assets/items.py
tests/__init__.py
tests/conftest.py
tests/helpers.py
tests/test_demcompare_gironde_data.py
tests/test_demcompare_gironde_test_data.py
tests/test_demcompare_srtm_data.py
tests/test_demcompare_steps.py
tests/test_img_tools.py
tests/test_notebooks.py
tests/test_stats_dataset.py
tests/test_tiling.py
tests/test_transformation.py
tests/classification_layer/__init__.py
tests/classification_layer/test_classification_layer.py
tests/classification_layer/test_fusion_classification.py
demcompare-0.6.1.dist-info/LICENSE
demcompare-0.6.1.dist-info/METADATA
demcompare-0.6.1.dist-info/WHEEL
demcompare-0.6.1.dist-info/entry_points.txt
demcompare-0.6.1.dist-info/top_level.txt
demcompare-0.6.1.dist-info/RECORD
