Metadata-Version: 2.1
Name: demcompare
Version: 0.6.1
Summary: A tool to compare Digital Elevation Models
Home-page: https://github.com/CNES/demcompare
Author: CNES
Author-email: cars@cnes.fr
License: Apache License 2.0
Keywords: demcompare,3D,DEM,cars,pandora,photogrammetry
Platform: any
Classifier: Development Status :: 4 - Beta
Classifier: Intended Audience :: Developers
Classifier: Intended Audience :: End Users/Desktop
Classifier: Intended Audience :: Science/Research
Classifier: Environment :: Console
Classifier: Topic :: Software Development :: Libraries :: Python Modules
Classifier: License :: OSI Approved :: Apache Software License
Classifier: Operating System :: OS Independent
Classifier: Programming Language :: Python
Classifier: Programming Language :: Python :: 3.8
Requires-Python: >=3.8
License-File: LICENSE
Requires-Dist: numpy
Requires-Dist: matplotlib >=3.5.1
Requires-Dist: xarray >=0.13.0
Requires-Dist: pyarrow
Requires-Dist: scipy !=1.10.0
Requires-Dist: rasterio
Requires-Dist: pyproj
Requires-Dist: astropy
Requires-Dist: sphinx
Requires-Dist: lib-programname
Requires-Dist: argcomplete
Requires-Dist: json-checker
Requires-Dist: dash-bootstrap-components
Provides-Extra: dev
Requires-Dist: pre-commit ; extra == 'dev'
Requires-Dist: isort >=5.8.0 ; extra == 'dev'
Requires-Dist: black[jupyter] >=21.5b0 ; extra == 'dev'
Requires-Dist: flake8 >=3.9.1 ; extra == 'dev'
Requires-Dist: flake8-comprehensions >=3.4.0 ; extra == 'dev'
Requires-Dist: flake8-bugbear >=21.4.3 ; extra == 'dev'
Requires-Dist: pylint !=3.2.4 ; extra == 'dev'
Requires-Dist: setuptools-scm ; extra == 'dev'
Requires-Dist: virtualenv ; extra == 'dev'
Requires-Dist: twine ; extra == 'dev'
Requires-Dist: build ; extra == 'dev'
Requires-Dist: pytest ; extra == 'dev'
Requires-Dist: pytest-cov ; extra == 'dev'
Requires-Dist: pytest-sugar ; extra == 'dev'
Requires-Dist: tox ; extra == 'dev'
Requires-Dist: mypy ; extra == 'dev'
Provides-Extra: docs
Requires-Dist: sphinx >=4.3.0 ; extra == 'docs'
Requires-Dist: sphinx-rtd-theme >=0.5.1 ; extra == 'docs'
Requires-Dist: sphinx-autoapi ; extra == 'docs'
Requires-Dist: sphinx-tabs ; extra == 'docs'
Provides-Extra: notebook
Requires-Dist: bokeh ; extra == 'notebook'
Requires-Dist: matplotlib ; extra == 'notebook'
Requires-Dist: notebook ; extra == 'notebook'
Requires-Dist: tabulate ; extra == 'notebook'
Requires-Dist: jupyter-dash ; extra == 'notebook'
